{
    "dataType": "Constellation",
    "ark": "http:\/\/n2t.net\/ark:\/99166\/w6ss4hvt",
    "entityType": {
        "id": "698",
        "term": "corporateBody",
        "uri": "http:\/\/socialarchive.iath.virginia.edu\/control\/term#CorporateBody",
        "type": "entity_type"
    },
    "maintenanceStatus": {
        "term": "revised"
    },
    "maintenanceAgency": "SNAC: Social Networks and Archival Context",
    "maintenanceEvents": [
        {
            "dataType": "MaintenanceEvent",
            "eventType": {
                "id": "704",
                "term": "revised"
            },
            "eventDateTime": "2015-05-07",
            "agentType": {
                "id": "687",
                "term": "machine"
            },
            "agent": "CPF merge program",
            "eventDescription": "Merge v2.0"
        },
        {
            "dataType": "MaintenanceEvent",
            "eventType": {
                "id": "704",
                "term": "revised",
                "type": "event_type"
            },
            "eventDateTime": "2016-08-16T05:09:09",
            "standardDateTime": "2016-08-16T05:09:09",
            "agentType": {
                "id": "687",
                "term": "machine",
                "type": "agent_type"
            },
            "agent": "SNAC EAC-CPF Parser",
            "eventDescription": "Bulk ingest into SNAC Database"
        },
        {
            "dataType": "MaintenanceEvent",
            "eventType": {
                "id": "704",
                "term": "revised",
                "type": "event_type"
            },
            "eventDateTime": "2016-08-16T05:09:09",
            "standardDateTime": "2016-08-16T05:09:09",
            "agentType": {
                "id": "400254",
                "term": "human",
                "type": "agent_type"
            },
            "agent": "System Service (system@localhost)"
        }
    ],
    "sources": [
        {
            "dataType": "Source",
            "type": {
                "id": "28296",
                "term": "simple",
                "type": "source_type"
            },
            "text": "<objectXMLWrap>\n               <container xmlns=\"\">\n                  <filename>\/data\/source\/findingAids\/nyu\/archives\/maccracken.xml<\/filename>\n                  <ead_entity en_type=\"corpname\" rules=\"dacs\" source=\"local\">New York University. Washington Square College of Arts and Science.<\/ead_entity>\n               <\/container>\n            <\/objectXMLWrap>",
            "uri": "http:\/\/dlib.nyu.edu\/findingaids\/html\/archives\/maccracken\/maccracken.html",
            "id": "56431096",
            "version": "8254601"
        },
        {
            "dataType": "Source",
            "type": {
                "id": "28296",
                "term": "simple",
                "type": "source_type"
            },
            "text": "<objectXMLWrap>\n               <container xmlns=\"\">\n                  <filename>\/data\/source\/findingAids\/nyu\/archives\/alumnifed.xml<\/filename>\n                  <ead_entity en_type=\"corpname\" rules=\"dacs\" source=\"local\">New York University. Washington Square College of Arts and Science.<\/ead_entity>\n               <\/container>\n            <\/objectXMLWrap>",
            "uri": "http:\/\/dlib.nyu.edu\/findingaids\/html\/archives\/alumnifed\/alumnifed.html",
            "id": "56431095",
            "version": "8254601"
        },
        {
            "dataType": "Source",
            "type": {
                "id": "28296",
                "term": "simple",
                "type": "source_type"
            },
            "text": "<objectXMLWrap>\n               <container xmlns=\"\">\n                  <filename>\/data\/source\/findingAids\/nyu\/archives\/bradley.xml<\/filename>\n                  <ead_entity en_type=\"corpname\" source=\"ingest\">New York University. Washington Square College of Arts and Science.<\/ead_entity>\n               <\/container>\n            <\/objectXMLWrap>",
            "uri": "http:\/\/dlib.nyu.edu\/findingaids\/html\/archives\/bradley\/bradley.html",
            "id": "56431093",
            "version": "8254601"
        },
        {
            "dataType": "Source",
            "type": {
                "id": "28296",
                "term": "simple",
                "type": "source_type"
            },
            "text": "<objectXMLWrap>\n               <container xmlns=\"\">\n                  <filename>\/data\/source\/findingAids\/nyu\/archives\/satc.xml<\/filename>\n                  <ead_entity en_type=\"corpname\" rules=\"dacs\" source=\"local\">New York University. Washington Square College of Arts and Science.<\/ead_entity>\n               <\/container>\n            <\/objectXMLWrap>",
            "uri": "http:\/\/dlib.nyu.edu\/findingaids\/html\/archives\/satc\/satc.html",
            "id": "56431094",
            "version": "8254601"
        }
    ],
    "nameEntries": [
        {
            "dataType": "NameEntry",
            "original": "New York University. Washington Square College of Arts and Science.",
            "preferenceScore": "1",
            "components": [
                {
                    "dataType": "NameComponent",
                    "text": "New York University. Washington Square College of Arts and Science.",
                    "order": "0",
                    "type": {
                        "id": "400228",
                        "term": "Name",
                        "type": "name_component"
                    },
                    "id": "56431098",
                    "version": "8254601"
                }
            ],
            "id": "56431097",
            "version": "8254601",
            "snacControlMetadata": [
                {
                    "dataType": "SNACControlMetadata",
                    "sourceData": "[\n    {\n        \"contributor\": \"nyu\",\n        \"form\": \"authorizedForm\"\n    }\n]",
                    "note": "Contributors from initial SNAC EAC-CPF ingest",
                    "id": "81420947",
                    "version": "8254601"
                }
            ]
        }
    ],
    "relations": [
        {
            "dataType": "ConstellationRelation",
            "sourceConstellation": "56431092",
            "targetConstellation": "60668214",
            "sourceArkID": "http:\/\/n2t.net\/ark:\/99166\/w6ss4hvt",
            "targetArkID": "http:\/\/n2t.net\/ark:\/99166\/w6vf3m13",
            "targetEntityType": {
                "id": "698",
                "term": "corporateBody",
                "uri": "http:\/\/socialarchive.iath.virginia.edu\/control\/term#CorporateBody",
                "type": "entity_type"
            },
            "type": {
                "id": "28234",
                "term": "associatedWith",
                "uri": "http:\/\/socialarchive.iath.virginia.edu\/control\/term#associatedWith",
                "type": "relation_type"
            },
            "content": "Alumni Federation of New York University, Inc.",
            "id": "56431106",
            "version": "8254601"
        },
        {
            "dataType": "ConstellationRelation",
            "sourceConstellation": "56431092",
            "targetConstellation": "15197949",
            "sourceArkID": "http:\/\/n2t.net\/ark:\/99166\/w6ss4hvt",
            "targetArkID": "http:\/\/n2t.net\/ark:\/99166\/w63n2hsk",
            "targetEntityType": {
                "id": "700",
                "term": "person",
                "uri": "http:\/\/socialarchive.iath.virginia.edu\/control\/term#Person",
                "type": "entity_type"
            },
            "type": {
                "id": "28234",
                "term": "associatedWith",
                "uri": "http:\/\/socialarchive.iath.virginia.edu\/control\/term#associatedWith",
                "type": "relation_type"
            },
            "content": "Brown, Marshall Stewart, 1870-1948",
            "id": "56431105",
            "version": "8254601"
        },
        {
            "dataType": "ConstellationRelation",
            "sourceConstellation": "56431092",
            "targetConstellation": "74368098",
            "sourceArkID": "http:\/\/n2t.net\/ark:\/99166\/w6ss4hvt",
            "targetArkID": "http:\/\/n2t.net\/ark:\/99166\/w6g79bqj",
            "targetEntityType": {
                "id": "698",
                "term": "corporateBody",
                "uri": "http:\/\/socialarchive.iath.virginia.edu\/control\/term#CorporateBody",
                "type": "entity_type"
            },
            "type": {
                "id": "28234",
                "term": "associatedWith",
                "uri": "http:\/\/socialarchive.iath.virginia.edu\/control\/term#associatedWith",
                "type": "relation_type"
            },
            "content": "Office of the Secretary",
            "id": "56431104",
            "version": "8254601"
        }
    ],
    "resourceRelations": [
        {
            "dataType": "ResourceRelation",
            "resource": {
                "dataType": "Resource",
                "documentType": {
                    "id": "696",
                    "term": "ArchivalResource",
                    "uri": "http:\/\/socialarchive.iath.virginia.edu\/control\/term#ArchivalResource",
                    "type": "document_type"
                },
                "link": "http:\/\/dlib.nyu.edu\/findingaids\/html\/archives\/alumnifed\/alumnifed.html",
                "source": "<objectXMLWrap>\n               <did xmlns=\"urn:isbn:1-931666-22-9\">\n                  <unittitle>Records of the Alumni Federation of New York University, Inc.<\/unittitle>\n                  <unitid>RG 40.7<\/unitid>\n                  <repository>\n                     <corpname>New York University Archives<\/corpname>\n                  <\/repository>\n                  <langmaterial>\n                     <language\/>\n                  <\/langmaterial>\n                  <physdesc>\n                     <extent>12.1 linear feet<\/extent>\n                     <extent>(10 boxes)<\/extent>\n                  <\/physdesc>\n                  <unitdate>Bulk, 1919-1945<\/unitdate>\n                  <unitdate>1919-1992<\/unitdate>\n                  <origination>\n                     <corpname>Alumni Federation of New York University, Inc.<\/corpname>\n                  <\/origination>\n               <\/did>\n            <\/objectXMLWrap>",
                "title": "Records of the Alumni Federation of New York University, Inc. Bulk, 1919-1945 1919-1992",
                "extent": "12.1 linear feet; (10 boxes)",
                "displayEntry": "Records of the Alumni Federation of New York University, Inc., Bulk, 1919-1945, 1919-1992",
                "repository": {
                    "dataType": "Constellation",
                    "ark": "http:\/\/n2t.net\/ark:\/99166\/w6wf4pnp",
                    "entityType": {
                        "id": "698",
                        "term": "corporateBody",
                        "uri": "http:\/\/socialarchive.iath.virginia.edu\/control\/term#CorporateBody",
                        "type": "entity_type"
                    },
                    "nameEntries": [
                        {
                            "dataType": "NameEntry",
                            "original": "New York University. Archives",
                            "preferenceScore": "99",
                            "id": "83696240",
                            "version": "11327358"
                        }
                    ],
                    "places": [
                        {
                            "dataType": "Place",
                            "original": "New York University Archives",
                            "type": {
                                "id": "400242",
                                "term": "Address",
                                "uri": "http:\/\/socialarchive.iath.virginia.edu\/control\/term#Address",
                                "type": "place_type"
                            },
                            "address": [
                                {
                                    "dataType": "AddressLine",
                                    "text": "70 Washington Square South  10th Fl.  New York, New York 10012  United States",
                                    "order": "0",
                                    "type": {
                                        "id": "400243",
                                        "term": "Unspecified",
                                        "uri": "http:\/\/socialarchive.iath.virginia.edu\/control\/term#Unspecified",
                                        "type": "address_part"
                                    },
                                    "id": "83696245",
                                    "version": "11285391"
                                }
                            ],
                            "id": "83696244",
                            "version": "11285391"
                        }
                    ],
                    "id": "83696236",
                    "version": "11327359"
                },
                "id": "6328753",
                "version": "6328753"
            },
            "role": {
                "id": "693",
                "term": "referencedIn",
                "uri": "http:\/\/socialarchive.iath.virginia.edu\/control\/term#referencedIn",
                "type": "document_role"
            },
            "content": "Records of the Alumni Federation of New York University, Inc., Bulk, 1919-1945, 1919-1992",
            "id": "56431109",
            "version": "8254601"
        },
        {
            "dataType": "ResourceRelation",
            "resource": {
                "dataType": "Resource",
                "documentType": {
                    "id": "696",
                    "term": "ArchivalResource",
                    "uri": "http:\/\/socialarchive.iath.virginia.edu\/control\/term#ArchivalResource",
                    "type": "document_type"
                },
                "link": "http:\/\/dlib.nyu.edu\/findingaids\/html\/archives\/maccracken\/maccracken.html",
                "source": "<objectXMLWrap>\n               <did xmlns=\"urn:isbn:1-931666-22-9\">\n                  <unittitle>Records of the Office of the Chancellor (Henry MacCracken)<\/unittitle>\n                  <unitid>RG 3.0.3<\/unitid>\n                  <repository>\n                     <corpname>New York University Archives<\/corpname>\n                  <\/repository>\n                  <langmaterial>\n                     <language\/>\n                  <\/langmaterial>\n                  <physdesc>\n                     <extent>12.5 linear feet<\/extent>\n                  <\/physdesc>\n                  <unitdate>1884-1910<\/unitdate>\n                  <abstract>The Records of the Henry M. MacCracken Administration have been divided into nine series containing materials that pertain to MacCracken's activities as vice chancellor and chancellor of New York University.<\/abstract>\n               <\/did>\n            <\/objectXMLWrap>",
                "title": "Records of the Office of the Chancellor (Henry MacCracken) 1884-1910",
                "abstract": "The Records of the Henry M. MacCracken Administration have been divided into nine series containing materials that pertain to MacCracken's activities as vice chancellor and chancellor of New York University.",
                "extent": "12.5 linear feet",
                "displayEntry": "Records of the Office of the Chancellor (Henry MacCracken), 1884-1910",
                "repository": {
                    "dataType": "Constellation",
                    "ark": "http:\/\/n2t.net\/ark:\/99166\/w6wf4pnp",
                    "entityType": {
                        "id": "698",
                        "term": "corporateBody",
                        "uri": "http:\/\/socialarchive.iath.virginia.edu\/control\/term#CorporateBody",
                        "type": "entity_type"
                    },
                    "nameEntries": [
                        {
                            "dataType": "NameEntry",
                            "original": "New York University. Archives",
                            "preferenceScore": "99",
                            "id": "83696240",
                            "version": "11327358"
                        }
                    ],
                    "places": [
                        {
                            "dataType": "Place",
                            "original": "New York University Archives",
                            "type": {
                                "id": "400242",
                                "term": "Address",
                                "uri": "http:\/\/socialarchive.iath.virginia.edu\/control\/term#Address",
                                "type": "place_type"
                            },
                            "address": [
                                {
                                    "dataType": "AddressLine",
                                    "text": "70 Washington Square South  10th Fl.  New York, New York 10012  United States",
                                    "order": "0",
                                    "type": {
                                        "id": "400243",
                                        "term": "Unspecified",
                                        "uri": "http:\/\/socialarchive.iath.virginia.edu\/control\/term#Unspecified",
                                        "type": "address_part"
                                    },
                                    "id": "83696245",
                                    "version": "11285391"
                                }
                            ],
                            "id": "83696244",
                            "version": "11285391"
                        }
                    ],
                    "id": "83696236",
                    "version": "11327359"
                },
                "id": "6328848",
                "version": "6328848"
            },
            "role": {
                "id": "693",
                "term": "referencedIn",
                "uri": "http:\/\/socialarchive.iath.virginia.edu\/control\/term#referencedIn",
                "type": "document_role"
            },
            "content": "Records of the Office of the Chancellor (Henry MacCracken), 1884-1910",
            "id": "56431110",
            "version": "8254601"
        },
        {
            "dataType": "ResourceRelation",
            "resource": {
                "dataType": "Resource",
                "documentType": {
                    "id": "696",
                    "term": "ArchivalResource",
                    "uri": "http:\/\/socialarchive.iath.virginia.edu\/control\/term#ArchivalResource",
                    "type": "document_type"
                },
                "link": "http:\/\/dlib.nyu.edu\/findingaids\/html\/archives\/satc\/satc.html",
                "source": "<objectXMLWrap>\n               <did xmlns=\"urn:isbn:1-931666-22-9\">\n                  <unittitle>Records of the Student Army Training Corps<\/unittitle>\n                  <unitid>RG 43.1<\/unitid>\n                  <repository>\n                     <corpname>New York University Archives<\/corpname>\n                  <\/repository>\n                  <langmaterial>\n                     <language\/>\n                  <\/langmaterial>\n                  <physdesc>\n                     <extent>2.0 linear feet<\/extent>\n                     <extent>(5 boxes)<\/extent>\n                  <\/physdesc>\n                  <unitdate>1916-1921<\/unitdate>\n                  <abstract>The records of the Student Army Training Corps Program (SATC) unit are part of the papers of Dean Marshall S. Brown, who served as chairman of NYU's SATC Committee from September 1918 to the following spring. The material includes both internal and external correspondence and memoranda, mainly between the members of NYU's SATC Committee and officials in various government departments.<\/abstract>\n                  <origination>\n                     <persname>Brown, Marshall Stewart, 1870-1948<\/persname>\n                  <\/origination>\n               <\/did>\n            <\/objectXMLWrap>",
                "title": "Records of the Student Army Training Corps 1916-1921",
                "abstract": "The records of the Student Army Training Corps Program (SATC) unit are part of the papers of Dean Marshall S. Brown, who served as chairman of NYU's SATC Committee from September 1918 to the following spring. The material includes both internal and external correspondence and memoranda, mainly between the members of NYU's SATC Committee and officials in various government departments.",
                "extent": "2.0 linear feet; (5 boxes)",
                "displayEntry": "Records of the Student Army Training Corps, 1916-1921",
                "originationNames": [
                    {
                        "dataType": "OriginationName",
                        "name": "Brown, Marshall Stewart, 1870-1948",
                        "id": "11357028",
                        "version": "6328889"
                    }
                ],
                "repository": {
                    "dataType": "Constellation",
                    "ark": "http:\/\/n2t.net\/ark:\/99166\/w6wf4pnp",
                    "entityType": {
                        "id": "698",
                        "term": "corporateBody",
                        "uri": "http:\/\/socialarchive.iath.virginia.edu\/control\/term#CorporateBody",
                        "type": "entity_type"
                    },
                    "nameEntries": [
                        {
                            "dataType": "NameEntry",
                            "original": "New York University. Archives",
                            "preferenceScore": "99",
                            "id": "83696240",
                            "version": "11327358"
                        }
                    ],
                    "places": [
                        {
                            "dataType": "Place",
                            "original": "New York University Archives",
                            "type": {
                                "id": "400242",
                                "term": "Address",
                                "uri": "http:\/\/socialarchive.iath.virginia.edu\/control\/term#Address",
                                "type": "place_type"
                            },
                            "address": [
                                {
                                    "dataType": "AddressLine",
                                    "text": "70 Washington Square South  10th Fl.  New York, New York 10012  United States",
                                    "order": "0",
                                    "type": {
                                        "id": "400243",
                                        "term": "Unspecified",
                                        "uri": "http:\/\/socialarchive.iath.virginia.edu\/control\/term#Unspecified",
                                        "type": "address_part"
                                    },
                                    "id": "83696245",
                                    "version": "11285391"
                                }
                            ],
                            "id": "83696244",
                            "version": "11285391"
                        }
                    ],
                    "id": "83696236",
                    "version": "11327359"
                },
                "id": "6328889",
                "version": "6328889"
            },
            "role": {
                "id": "693",
                "term": "referencedIn",
                "uri": "http:\/\/socialarchive.iath.virginia.edu\/control\/term#referencedIn",
                "type": "document_role"
            },
            "content": "Records of the Student Army Training Corps, 1916-1921",
            "id": "56431108",
            "version": "8254601"
        },
        {
            "dataType": "ResourceRelation",
            "resource": {
                "dataType": "Resource",
                "documentType": {
                    "id": "696",
                    "term": "ArchivalResource",
                    "uri": "http:\/\/socialarchive.iath.virginia.edu\/control\/term#ArchivalResource",
                    "type": "document_type"
                },
                "link": "http:\/\/dlib.nyu.edu\/findingaids\/html\/archives\/bradley\/bradley.html",
                "source": "<objectXMLWrap>\n               <did xmlns=\"urn:isbn:1-931666-22-9\">\n                  <unittitle>Records of the Lyman R. Bradley Academic Freedom Case<\/unittitle>\n                  <unitid>RG 19.2<\/unitid>\n                  <repository>\n                     <corpname>New York University Archives<\/corpname>\n                  <\/repository>\n                  <langmaterial>\n                     <language\/>\n                  <\/langmaterial>\n                  <physdesc>\n                     <extent>4.0 Linear feet<\/extent>\n                     <extent>4 linear feet (6 boxes)<\/extent>\n                  <\/physdesc>\n                  <unitdate>1947-1961<\/unitdate>\n                  <physloc>11\/D\/3-4<\/physloc>\n                  <abstract>The Records of the Lyman R. Bradley Academic Freedom Case detail the action of New York University in hearing charges and subsequent suspension of a tenured associate professor who was convicted of contempt of Congress in 1948. The collection consists of administrative records retained by three offices of the University: the Office of the Dean of Washington Square College; the Office of the Chancellor; and the Office of the Vice Chancellor, who as Secretary and Clerk of the University Council (later Board of Trustees) maintained the Council files.<\/abstract>\n                  <origination>\n                     <corpname>Office of the Secretary<\/corpname>\n                  <\/origination>\n               <\/did>\n            <\/objectXMLWrap>",
                "title": "Records of the Lyman R. Bradley Academic Freedom Case 1947-1961",
                "abstract": "The Records of the Lyman R. Bradley Academic Freedom Case detail the action of New York University in hearing charges and subsequent suspension of a tenured associate professor who was convicted of contempt of Congress in 1948. The collection consists of administrative records retained by three offices of the University: the Office of the Dean of Washington Square College; the Office of the Chancellor; and the Office of the Vice Chancellor, who as Secretary and Clerk of the University Council (later Board of Trustees) maintained the Council files.",
                "extent": "4.0 Linear feet; 4 linear feet (6 boxes)",
                "displayEntry": "Records of the Lyman R. Bradley Academic Freedom Case, 1947-1961",
                "repository": {
                    "dataType": "Constellation",
                    "ark": "http:\/\/n2t.net\/ark:\/99166\/w6wf4pnp",
                    "entityType": {
                        "id": "698",
                        "term": "corporateBody",
                        "uri": "http:\/\/socialarchive.iath.virginia.edu\/control\/term#CorporateBody",
                        "type": "entity_type"
                    },
                    "nameEntries": [
                        {
                            "dataType": "NameEntry",
                            "original": "New York University. Archives",
                            "preferenceScore": "99",
                            "id": "83696240",
                            "version": "11327358"
                        }
                    ],
                    "places": [
                        {
                            "dataType": "Place",
                            "original": "New York University Archives",
                            "type": {
                                "id": "400242",
                                "term": "Address",
                                "uri": "http:\/\/socialarchive.iath.virginia.edu\/control\/term#Address",
                                "type": "place_type"
                            },
                            "address": [
                                {
                                    "dataType": "AddressLine",
                                    "text": "70 Washington Square South  10th Fl.  New York, New York 10012  United States",
                                    "order": "0",
                                    "type": {
                                        "id": "400243",
                                        "term": "Unspecified",
                                        "uri": "http:\/\/socialarchive.iath.virginia.edu\/control\/term#Unspecified",
                                        "type": "address_part"
                                    },
                                    "id": "83696245",
                                    "version": "11285391"
                                }
                            ],
                            "id": "83696244",
                            "version": "11285391"
                        }
                    ],
                    "id": "83696236",
                    "version": "11327359"
                },
                "id": "6328775",
                "version": "6328775"
            },
            "role": {
                "id": "693",
                "term": "referencedIn",
                "uri": "http:\/\/socialarchive.iath.virginia.edu\/control\/term#referencedIn",
                "type": "document_role"
            },
            "content": "Records of the Lyman R. Bradley Academic Freedom Case, 1947-1961",
            "id": "56431107",
            "version": "8254601"
        }
    ],
    "id": "56431092",
    "version": "8254602"
}